{
  "formatVersion": "1",
  "header": {
    "description": "Maintain Partner Function for Port Code",
    "originalLanguage": "en",
    "abapLanguageVersion": "cloudDevelopment"
  },
  "serviceConfiguration": {
    "serviceBinding": "ZUI_PARTNERFUNCTIONFORP_O4",
    "serviceName": "ZUI_PARTNERFUNCTIONFORP_O4",
    "serviceVersion": "0001",
    "rootEntitySet": "PartnerFunctionFAll",
    "name": "Partner Function for Port Code",
    "transportObject": "",
    "configurationGroup": "",
    "skipRootEntity": true,
    "enableFileUpload": false
  },
  "appConfiguration": {
    "listReport": {},
    "objectPages": [
      {
        "entitySet": "PartnerFunctionFAll",
        "variantManagement": "control",
        "showTransportSelectionStrip": true
      }
    ],
    "tableSettings": [
      {
        "entitySet": "PartnerFunctionForP",
        "tableType": "gridTable",
        "selectAll": true,
        "rowCountMode": "auto",
        "frozenColumnCount": 1,
        "creationModeName": "inlineCreationRows",
        "createAtEnd": true,
        "widthIncludingColumnHeader": true
      }
    ]
  }
}
